shapely_polyskel/__init__.py
shapely_polyskel/polyskel.py
shapely_polyskel/shapely_polyskel.py
shapely_polyskel-0.1.2.dist-info/LICENSE
shapely_polyskel-0.1.2.dist-info/METADATA
shapely_polyskel-0.1.2.dist-info/WHEEL
shapely_polyskel-0.1.2.dist-info/top_level.txt
shapely_polyskel-0.1.2.dist-info/RECORD
