Metadata-Version: 2.1
Name: shapely-polyskel
Version: 0.1.2
Summary: Implementation of the straight skeleton algorithm as described by Felkel and Obdržálek in their 1998 conference paper Straight skeleton implementation.
Author: Ármin Scipiades, vec2pt
Maintainer: vec2pt
License:                    GNU LESSER GENERAL PUBLIC LICENSE
Project-URL: Homepage, https://github.com/vec2pt/shapely-polyskel
Project-URL: Repository, https://github.com/vec2pt/shapely-polyskel.git
Project-URL: Issues, https://github.com/vec2pt/shapely-polyskel/issues
Keywords: shapely,geometry,polygon,straight skeleton
Classifier: Development Status :: 4 - Beta
Classifier: Intended Audience :: Developers
Classifier: Intended Audience :: Science/Research
Classifier: Topic :: Scientific/Engineering :: GIS
Classifier: License :: OSI Approved :: GNU Lesser General Public License v3 (LGPLv3)
Classifier: Operating System :: Unix
Classifier: Operating System :: MacOS
Classifier: Operating System :: Microsoft :: Windows
Classifier: Programming Language :: Python :: 3
Classifier: Programming Language :: Python :: 3.10
Classifier: Programming Language :: Python :: 3.11
Classifier: Programming Language :: Python :: 3.12
Requires-Python: >=3.10
License-File: LICENSE
Requires-Dist: euclid3==0.1
Requires-Dist: shapely>=2.0.5
Provides-Extra: test
Requires-Dist: pytest; extra == "test"
Provides-Extra: dev
Requires-Dist: ruff; extra == "dev"
